alex/__init__.py
alex/instagram.py
alex/naver_news.py
test/__init__.py
test/instagram_test.py
test/test_naver_news.py
alex_junior-0.24.dist-info/METADATA
alex_junior-0.24.dist-info/WHEEL
alex_junior-0.24.dist-info/top_level.txt
alex_junior-0.24.dist-info/RECORD
