Metadata-Version: 2.1
Name: alex-junior
Version: 0.24
Summary: Just for fun
Home-page: https://github.com/shaynekang/alex-junior
Author: DS School
Author-email: support@dsschool.co.kr
License: UNKNOWN
Platform: UNKNOWN
Classifier: Programming Language :: Python :: 3
Classifier: License :: OSI Approved :: MIT License
Classifier: Operating System :: OS Independent
